tests/mock_device.py
tests/test_devices.py
tests/__init__.py
tests/test_sensors.py
tests/smoke_tests/test_commands.py
tests/smoke_tests/__init__.py
zorg_gpio-0.0.7.dist-info/RECORD
zorg_gpio-0.0.7.dist-info/top_level.txt
zorg_gpio-0.0.7.dist-info/metadata.json
zorg_gpio-0.0.7.dist-info/zip-safe
zorg_gpio-0.0.7.dist-info/METADATA
zorg_gpio-0.0.7.dist-info/DESCRIPTION.rst
zorg_gpio-0.0.7.dist-info/WHEEL
zorg_gpio/led.py
zorg_gpio/light_sensor.py
zorg_gpio/digital_sensor.py
zorg_gpio/__init__.py
zorg_gpio/button.py
zorg_gpio/relay.py
zorg_gpio/analog_sensor.py
zorg_gpio/buzzer.py
